gne/__init__.py
gne/defaults.py
gne/utils.py
gne/extractor/AuthorExtractor.py
gne/extractor/ContentExtractor.py
gne/extractor/ListExtractor.py
gne/extractor/SourceExtractor.py
gne/extractor/TimeExtractor.py
gne/extractor/TitleExtractor.py
gne/extractor/__init__.py
gne_ren-0.3.1.dist-info/LICENSE
gne_ren-0.3.1.dist-info/METADATA
gne_ren-0.3.1.dist-info/WHEEL
gne_ren-0.3.1.dist-info/top_level.txt
gne_ren-0.3.1.dist-info/RECORD
